dompose/__init__.py
dompose/dompose.py
dompose-0.0.3.dist-info/METADATA
dompose-0.0.3.dist-info/WHEEL
dompose-0.0.3.dist-info/entry_points.txt
dompose-0.0.3.dist-info/top_level.txt
dompose-0.0.3.dist-info/RECORD
