Metadata-Version: 2.1
Name: dompose
Version: 0.0.3
Summary: A docker-compose wrapper. Compose your docker-compose files.
Home-page: https://github.com/rhyst/dompose
Author: Rhys Tyers
Author-email: 
License: UNKNOWN
Platform: UNKNOWN
Classifier: Development Status :: 3 - Alpha
Classifier: Intended Audience :: Developers
Classifier: Topic :: Software Development :: Build Tools
Classifier: Programming Language :: Python :: 3.7
Requires-Python: >=3.7
Requires-Dist: pyyaml
Requires-Dist: python-dotenv
